tools/__init__.py
tools/tuanalysis_functions.py
tuanalyzes-0.0.3.dist-info/LICENSE.txt
tuanalyzes-0.0.3.dist-info/METADATA
tuanalyzes-0.0.3.dist-info/WHEEL
tuanalyzes-0.0.3.dist-info/top_level.txt
tuanalyzes-0.0.3.dist-info/RECORD
