Metadata-Version: 2.1
Name: tuanalyzes
Version: 0.0.3
Summary: UNKNOWN
Home-page: https://github.com/ubunTuan/analysis-functions.git
Author: Tuan Anh Bui
Author-email: kevbui.29@gmail.com
License: MIT
Keywords: Analyses,EDA,Important variables
Platform: UNKNOWN
Requires-Dist: seaborn
Requires-Dist: matplotlib
Requires-Dist: sklearn
Requires-Dist: panda
Requires-Dist: numpy
Requires-Dist: statsmodels
Requires-Dist: eli5
